autoruncmd/__init__.py
autoruncmd/add.py
autoruncmd/c_init.py
autoruncmd/constants.py
autoruncmd/find.py
autoruncmd/main.py
autoruncmd/run.py
autoruncmd/v_n.py
pyautorun/__init__.py
pyautorun/add.py
pyautorun/c_init.py
pyautorun/constants.py
pyautorun/find.py
pyautorun/main.py
pyautorun/run.py
pyautorun/v_n.py
AutoRunCmd-0.1.1.dist-info/LICENSE
AutoRunCmd-0.1.1.dist-info/METADATA
AutoRunCmd-0.1.1.dist-info/WHEEL
AutoRunCmd-0.1.1.dist-info/entry_points.txt
AutoRunCmd-0.1.1.dist-info/top_level.txt
AutoRunCmd-0.1.1.dist-info/RECORD
