Metadata-Version: 2.1
Name: AutoRunCmd
Version: 0.1.1
Summary: Runs multi scripts with a simple line of prompt with a config dot file in your environment
Home-page: https://github.com/rakeshkanna-rk/pyautorun/
Author: Rakesh Kanna
Author-email: rakeshkanna0108@gmail.com
License: MIT
Project-URL: GitHub, https://github.com/rakeshkanna-rk/pyautorun/
Project-URL: PyPI, https://pypi.org/project/pyautorun/
Keywords: automation,build tools,makefile,python scripts,task runner,command-line tool,config file
Classifier: Programming Language :: Python :: 3
Classifier: License :: OSI Approved :: MIT License
Classifier: Operating System :: OS Independent
Classifier: Intended Audience :: Developers
Classifier: Topic :: Software Development :: Build Tools
Classifier: Topic :: Software Development :: Libraries :: Python Modules
Classifier: Topic :: System :: Software Distribution
Classifier: Topic :: System :: Systems Administration
Classifier: Topic :: Utilities
Classifier: Typing :: Typed
Classifier: Environment :: Console
Classifier: Natural Language :: English
Requires-Python: >=3.6
License-File: LICENSE
Requires-Dist: textPlay
